LICENSE.txt
MANIFEST.in
README.md
requirements.txt
setup.cfg
setup.py
versioneer.py
als/__init__.py
als.bcs.egg-info/PKG-INFO
als.bcs.egg-info/SOURCES.txt
als.bcs.egg-info/dependency_links.txt
als.bcs.egg-info/requires.txt
als.bcs.egg-info/top_level.txt
als/bcs/__init__.py
als/bcs/_version.py
als/bcs/data.py
als/bcs/find.py
als/bcs/ingest.py
als/bcs/scans.py
als/bcs/version.py
als/bcs/version_id.py