Metadata-Version: 2.1
Name: als.bcs
Version: 0.2.0
Summary: Extract data and metadata from text data files that were generated by BCS at the ALS
Home-page: https://github.com/als-computing/als.bcs
Author: Padraic Shafer
Author-email: pshafer@lbl.gov
License: UNKNOWN
Keywords: ALS BCS Data Metadata
Platform: UNKNOWN
Classifier: Development Status :: 4 - Beta
Classifier: Intended Audience :: Developers
Classifier: Intended Audience :: Science/Research
Classifier: Topic :: Scientific/Engineering :: Information Analysis
Classifier: Topic :: Utilities
Classifier: License :: OSI Approved :: BSD License
Classifier: Programming Language :: Python :: 3.8
Classifier: Programming Language :: Python :: 3.9
Classifier: Programming Language :: Python :: 3.10
Classifier: Operating System :: OS Independent
Classifier: Environment :: Console
License-File: LICENSE.txt
